fastapi_observability/__init__.py
fastapi_observability/instrumentation.py
fastapi_observability/middleware.py
fastapi_observability-1.0.0.dist-info/METADATA
fastapi_observability-1.0.0.dist-info/WHEEL
fastapi_observability-1.0.0.dist-info/RECORD
