Metadata-Version: 2.1
Name: fastapi-observability
Version: 1.0.0
Summary: A middleware and instrumentation library for FastAPI to enable Prometheus metrics and OpenTelemetry tracing.
License: AGPL-3.0
Author: Pavel
Author-email: mulin.pasha@gmail.com
Requires-Python: >=3.10,<4.0
Classifier: License :: OSI Approved :: GNU Affero General Public License v3
Classifier: Programming Language :: Python :: 3
Classifier: Programming Language :: Python :: 3.10
Classifier: Programming Language :: Python :: 3.11
Classifier: Programming Language :: Python :: 3.12
Classifier: Programming Language :: Python :: 3.13
Requires-Dist: fastapi (>0.112.2)
Requires-Dist: opentelemetry-api (>=1.27.0,<2.0.0)
Requires-Dist: opentelemetry-exporter-otlp (>=1.27.0,<2.0.0)
Requires-Dist: opentelemetry-instrumentation-fastapi (>=0.48b0,<0.49)
Requires-Dist: opentelemetry-instrumentation-logging (>=0.48b0,<0.49)
Requires-Dist: opentelemetry-sdk (>=1.27.0,<2.0.0)
Requires-Dist: prometheus-client (>=0.21.0,<0.22.0)
Requires-Dist: starlette (>=0.41.0)
